setup.py
Gaubin_dists/Binomialdistribution.py
Gaubin_dists/Gaussiandistribution.py
Gaubin_dists/Generaldistribution.py
Gaubin_dists/__init__.py
Gaubin_dists.egg-info/PKG-INFO
Gaubin_dists.egg-info/SOURCES.txt
Gaubin_dists.egg-info/dependency_links.txt
Gaubin_dists.egg-info/not-zip-safe
Gaubin_dists.egg-info/top_level.txt