Metadata-Version: 1.0
Name: Gaubin-dists
Version: 1.0
Summary: Gaussian and Binomial distributions
Home-page: UNKNOWN
Author: Chukwume Ijeh
Author-email: chukwume.ijeh@stu.cu.edu.ng
License: UNKNOWN
Platform: UNKNOWN
